valens/__init__.py
valens/api.py
valens/assets.py
valens/cli.py
valens/config.py
valens/database.py
valens/default_config.py
valens/demo.py
valens/models.py
valens/version.py
valens/frontend/index.css
valens/frontend/manifest.json
valens/frontend/service-worker.js
valens/frontend/valens-web-app-seed.js
valens/frontend/valens-web-app-seed_bg.wasm
valens/frontend/fonts/Roboto-Bold.woff
valens/frontend/fonts/Roboto-BoldItalic.woff
valens/frontend/fonts/Roboto-Italic.woff
valens/frontend/fonts/Roboto-Regular.woff
valens/frontend/fonts/fa-solid-900.ttf
valens/frontend/fonts/fa-solid-900.woff2
valens/frontend/images/android-chrome-192x192.png
valens/frontend/images/android-chrome-512x512.png
valens/frontend/images/apple-touch-icon.png
valens/frontend/images/favicon-16x16.png
valens/frontend/images/favicon-32x32.png
valens/frontend/js/clock.js
valens/frontend/js/register-sw.js
valens/migrations/env.py
valens/migrations/script.py.mako
valens/migrations/versions/06f82ead211b_merge_duration_and_tempo_in_routine_activity.py
valens/migrations/versions/22f3ddb25741_add_reps_weight_and_rpe_to_routine_activity.py
valens/migrations/versions/3e7317eb4efa_add_foreign_key_on_delete_cascade.py
valens/migrations/versions/4b6051594962_add_type_checking.py
valens/migrations/versions/4cacd61cb0c5_add_routine_id_to_workout.py
valens/migrations/versions/743cea459efa_add_muscles_trained_by_exercise.py
valens/migrations/versions/8a0dc258bf2a_extend_workouts.py
valens/migrations/versions/a6220efbbda7_fix_typo.py
valens/migrations/versions/b9f4e42c7135_add_routine_sections.py
valens/migrations/versions/e4bc50b8ecb9_add_archived_to_routine.py
valens/templates/frontend.html
valens/templates/manifest.json
valens-0.6.0.dist-info/METADATA
valens-0.6.0.dist-info/WHEEL
valens-0.6.0.dist-info/entry_points.txt
valens-0.6.0.dist-info/licenses/LICENSE
valens-0.6.0.dist-info/RECORD
