Metadata-Version: 2.4
Name: valens
Version: 0.6.0
Summary: An app for tracking your health and training progress.
Project-URL: Homepage, https://pypi.org/project/valens/
Project-URL: Changelog, https://github.com/treiher/valens/blob/main/CHANGELOG.md
Project-URL: Issues, https://github.com/treiher/valens/issues
Project-URL: Repository, https://github.com/treiher/valens
Author-email: Tobias Reiher <valens@ardeidae.de>
License: AGPL-3.0
License-File: LICENSE
Classifier: Development Status :: 5 - Production/Stable
Classifier: Environment :: Web Environment
Classifier: Intended Audience :: End Users/Desktop
Classifier: License :: OSI Approved :: GNU Affero General Public License v3
Classifier: Natural Language :: English
Classifier: Operating System :: POSIX :: Linux
Classifier: Programming Language :: Python :: 3 :: Only
Classifier: Programming Language :: Python :: 3.10
Classifier: Programming Language :: Python :: 3.11
Classifier: Programming Language :: Python :: 3.12
Classifier: Programming Language :: Python :: 3.13
Classifier: Topic :: Other/Nonlisted Topic
Requires-Python: <4,>=3.10
Requires-Dist: alembic<2,>=1.6
Requires-Dist: flask<4,>=3
Requires-Dist: sqlalchemy<3,>=2
